<?xml version="1.0" encoding="utf-8"?>
<!DOCTYPE hibernate-mapping PUBLIC "-//Hibernate/Hibernate Mapping DTD 3.0//EN"
"http://hibernate.sourceforge.net/hibernate-mapping-3.0.dtd">
<!-- 
    Mapping file autogenerated by MyEclipse Persistence Tools
-->
<hibernate-mapping>
    <class name="com.era.orm.Information" table="information" catalog="building">
        <id name="id" type="java.lang.Integer">
            <column name="id" />
            <generator class="native"></generator>
        </id>
        <property name="title" type="java.lang.String">
            <column name="title" length="225">
                <comment>名称</comment>
            </column>
        </property>
        <property name="comment" type="java.lang.String">
            <column name="comment" length="1000">
                <comment>内容</comment>
            </column>
        </property>
        <property name="logo" type="java.lang.String">
            <column name="logo" length="1000">
                <comment>logo</comment>
            </column>
        </property>
        <property name="addtime" type="java.lang.String">
            <column name="addtime" length="225">
                <comment>添加时间</comment>
            </column>
        </property>
        <property name="sort" type="java.lang.Integer">
            <column name="sort">
                <comment>排序</comment>
            </column>
        </property>
        <property name="review" type="java.lang.String">
            <column name="review">
                <comment>导读</comment>
            </column>
        </property>
    </class>
</hibernate-mapping>
